setup.py
beam_extended/__init__.py
beam_extended/examples/__init__.py
beam_extended/examples/simple.py
beam_extended/io/__init__.py
beam_extended/io/mongodbio.py
beam_extended/io/mongodbio_test.py
beam_extended_mongodbio.egg-info/PKG-INFO
beam_extended_mongodbio.egg-info/SOURCES.txt
beam_extended_mongodbio.egg-info/dependency_links.txt
beam_extended_mongodbio.egg-info/requires.txt
beam_extended_mongodbio.egg-info/top_level.txt