Metadata-Version: 2.1
Name: beam-extended-mongodbio
Version: 1.0.0
Summary: Extend Apache Beam python API with new modules with no cursor timeout
Home-page: https://github.com/kadriansyah/beam-extended-mongodbio
Author: Kiagus Arief Adriansyah
Author-email: kadriansyah@gmail.com
License: UNKNOWN
Keywords: Apache,Beam,python
Platform: UNKNOWN
Classifier: Programming Language :: Python :: 2
Classifier: License :: OSI Approved :: Apache Software License
Classifier: Operating System :: OS Independent
